{"upgradeData":[{"materials":[{"glade":2,"quantity":6,"name":"Fine Rope","iconCol":3,"id":"1B 54 78 C8","type":30,"iconRow":2},{"glade":0,"quantity":10,"name":"Charming Orb","iconCol":11,"id":"BF EC A4 B1","type":30,"iconRow":1},{"glade":0,"quantity":25,"name":"Charming Crystal","iconCol":3,"id":"D2 BC B1 46","type":30,"iconRow":1},{"glade":0,"quantity":1,"name":"Supyo Soul","iconCol":3,"id":"44 A7 50 F8","type":40,"iconRow":10}],"oniOrbs":22340,"baseItem":{"name":"Victory Belt","rank":4,"iconCol":15,"id":"A3 4B 3C 62","iconRow":26}}],"upgradesInto":[],"def":0,"hp":440,"description":"Its buckle has the power of the sea. Everyone envies this super belt.","iconCol":7,"iconRow":27,"str":0,"createData":[],"spr":0,"skill":"Reduces Water Element damage by 50%.","name":"Splash Belt","rank":5,"id":"26 5D 73 67"}