{"upgradeData":[{"materials":[{"glade":3,"quantity":6,"name":"L. Thunder Visor","iconCol":14,"id":"53 5A 16 81","type":30,"iconRow":9},{"glade":2,"quantity":5,"name":"U. Thunder Rocket","iconCol":15,"id":"E9 0B 1F 19","type":30,"iconRow":9},{"glade":2,"quantity":4,"name":"U. Awoken Crown","iconCol":12,"id":"BC 68 35 45","type":30,"iconRow":15},{"glade":0,"quantity":1,"name":"Illuminoct Soul","iconCol":0,"id":"B3 1A 2E 26","type":40,"iconRow":10}],"oniOrbs":65500,"baseItem":{"name":"Captain Launcher","rank":4,"iconCol":12,"id":"C6 54 85 E3","iconRow":25}}],"upgradesInto":[],"def":0,"hp":0,"description":"The pride of Captain Thunder. Lights up the path through any obstacle.","iconCol":14,"iconRow":25,"str":0,"createData":[],"spr":360,"skill":"Atk ↑ when attacking, 1% ↑ per hit, lasts 5 seconds.","name":"Photon Beam","rank":6,"id":"29 3F 67 F7"}