{"upgradeData":[{"materials":[{"glade":1,"quantity":6,"name":"S. King Bauble","iconCol":14,"id":"4A 9E 7B 87","type":30,"iconRow":10},{"glade":2,"quantity":4,"name":"U. King Gauntlets","iconCol":7,"id":"F7 E2 CA F9","type":30,"iconRow":13},{"glade":2,"quantity":5,"name":"U. Zazelmare Horn","iconCol":6,"id":"B1 FE 69 07","type":30,"iconRow":8},{"glade":0,"quantity":1,"name":"Smogmella Soul","iconCol":1,"id":"FB 78 05 19","type":40,"iconRow":10}],"oniOrbs":63800,"baseItem":{"name":"Kingly Great Sword","rank":4,"iconCol":15,"id":"4D 9C 8C 49","iconRow":25}}],"upgradesInto":[],"def":0,"hp":0,"description":"A gift from the water dragon god. The sword gives power to its wielder.","iconCol":4,"iconRow":28,"str":370,"createData":[],"spr":0,"skill":"Increases the power of Soultimate Moves by 50%.","name":"Water Dragonblade","rank":5,"id":"34 C7 69 2B"}