{"name":"Zazelmare's Ring","id":"4C 58 DB 4E","iconCol":7,"iconRow":23,"rank":5,"description":"A gem from the underworld sits on the immensely powerful, ultimate ring.","hp":0,"str":0,"spr":300,"def":70,"skill":"Start mission with a 100% Soul Meter charge.","upgradeData":[{"baseItem":{"name":"Zazel's Ruby Ring","id":"A3 33 39 5B","iconCol":5,"iconRow":23,"rank":4},"materials":[{"id":"9D 9F 67 E9","name":"S. Zazelmare Horn","type":30,"iconCol":6,"iconRow":5,"glade":1,"quantity":5},{"id":"0B AF 60 9E","name":"U. Zazelmare Claw","type":30,"iconCol":11,"iconRow":7,"glade":2,"quantity":5},{"id":"FF FA CA C3","name":"Glitzy's Skull","type":30,"iconCol":2,"iconRow":8,"glade":2,"quantity":6},{"id":"2C 79 19 77","name":"Washogun Soul","type":40,"iconCol":0,"iconRow":10,"glade":"","quantity":1}],"oniOrbs":63400}],"upgradesInto":[]}