{"upgradeData":[{"materials":[{"glade":0,"quantity":1,"name":"Demuncher Tooth","iconCol":0,"id":"A2 ED A5 D2","type":30,"iconRow":4},{"glade":0,"quantity":1,"name":"Mass Muttercloth","iconCol":8,"id":"41 90 33 BB","type":30,"iconRow":4},{"glade":0,"quantity":2,"name":"Heartful Crystal","iconCol":4,"id":"71 29 D5 D8","type":30,"iconRow":1},{"glade":0,"quantity":5,"name":"Heartful Shard","iconCol":4,"id":"D8 07 55 E3","type":30,"iconRow":0}],"oniOrbs":1080,"baseItem":{"name":"Dimmy Amulet","rank":2,"iconCol":0,"id":"B1 3C 69 DE","iconRow":29}}],"upgradesInto":[],"def":15,"hp":60,"description":"Protection amulet shaped like Blandon. For Yo-kai who don't feel like talking.","iconCol":6,"iconRow":29,"str":15,"createData":[],"spr":15,"skill":"Attracts less attention from foes.","name":"Blandon Amulet","rank":3,"id":"52 D3 26 45"}