{"upgradeData":[{"materials":[{"glade":1,"quantity":3,"name":"Glitzy's Spine","iconCol":0,"id":"F8 D7 72 24","type":30,"iconRow":8},{"glade":1,"quantity":2,"name":"Glitzy's Ribcage","iconCol":1,"id":"69 CA CD B4","type":30,"iconRow":8},{"glade":0,"quantity":2,"name":"Glitzy's Pelvis","iconCol":14,"id":"D4 B6 7C CA","type":30,"iconRow":7},{"glade":0,"quantity":1,"name":"Glitzy's Tooth","iconCol":15,"id":"6E E7 75 53","type":30,"iconRow":7}],"oniOrbs":10110,"baseItem":{"name":"Gleaming Ring","rank":3,"iconCol":4,"id":"BF 15 4D 53","iconRow":19}}],"upgradesInto":[{"name":"Blue-Blood Ring","rank":5,"iconCol":10,"id":"55 9C B6 49","iconRow":20},{"name":"Blood-Red Ring","rank":5,"iconCol":11,"id":"EF CD BF D0","iconRow":20},{"name":"Diamond Ring","rank":5,"iconCol":12,"id":"79 FD B8 A7","iconRow":20}],"def":70,"hp":0,"description":"Lowers power and increases magic. Glitzy Bones's curse and blessing.","iconCol":12,"iconRow":19,"str":-30,"createData":[],"spr":180,"skill":"","name":"Glitzy Ring","rank":4,"id":"88 7F 8F 52"}