{"upgradeData":[],"upgradesInto":[{"name":"Mahogany Mallet","rank":3,"iconCol":24,"id":"C1 79 3D 14","iconRow":30}],"def":0,"hp":0,"description":"A small mallet made for a mouse. Small, but can pack a mean pounding.","iconCol":25,"iconRow":30,"str":80,"createData":[{"materials":[{"glade":0,"quantity":1,"name":"Samurai Armor","iconCol":22,"id":"C5 87 5E 12","type":30,"iconRow":30},{"glade":0,"quantity":1,"name":"Samurai Sword","iconCol":20,"id":"C5 87 5E 13","type":30,"iconRow":30},{"glade":0,"quantity":3,"name":"Brave Essence","iconCol":8,"id":"4E 37 52 94","type":30,"iconRow":0}],"oniOrbs":950}],"spr":0,"skill":"","name":"Mouse Mallet","rank":2,"id":"C1 79 3D 13"}