{"upgradeData":[{"materials":[{"glade":2,"quantity":3,"name":"Hound Skull Bomb","iconCol":4,"id":"6D 0F A1 D0","type":30,"iconRow":6},{"glade":0,"quantity":1,"name":"Komajiro Soul","iconCol":3,"id":"43 8A E8 1F","type":40,"iconRow":10},{"glade":0,"quantity":5,"name":"Charming Orb","iconCol":11,"id":"BF EC A4 B1","type":30,"iconRow":1},{"glade":0,"quantity":10,"name":"Charming Crystal","iconCol":3,"id":"D2 BC B1 46","type":30,"iconRow":1}],"oniOrbs":38000,"baseItem":{"name":"Swirly Pack","rank":4,"iconCol":7,"id":"C1 79 3D 04","iconRow":17}}],"upgradesInto":[],"def":170,"hp":200,"description":"A pack stuffed with hope to beat the odds in the city, in one way or another.","iconCol":21,"iconRow":31,"str":150,"createData":[],"spr":250,"skill":"Defense up by 210% when below 25% HP.","name":"Specter Sack","rank":5,"id":"C1 79 3D 06"}