{"upgradeData":[],"upgradesInto":[],"def":100,"hp":85,"description":"A charm with a four-leaf clover. Maybe something good will happen.","iconCol":14,"iconRow":24,"str":0,"createData":[{"materials":[{"glade":0,"quantity":2,"name":"Orcanos Spike","iconCol":7,"id":"28 FB D6 AD","type":30,"iconRow":3},{"glade":0,"quantity":1,"name":"Robonyan Motor","iconCol":9,"id":"91 42 0B B7","type":30,"iconRow":6},{"glade":0,"quantity":3,"name":"Eerie Orb","iconCol":14,"id":"29 DC A3 C6","type":30,"iconRow":1},{"glade":0,"quantity":4,"name":"Eerie Crystal","iconCol":6,"id":"44 8C B6 31","type":30,"iconRow":1}],"oniOrbs":6920}],"spr":0,"skill":"Avoids enemy attacks every now and then.","name":"Clover Charm","rank":4,"id":"E9 5C 55 09"}